pydaggerjl/__init__.py
pydaggerjl/core.py
pydaggerjl-0.1.0.dist-info/LICENSE.md
pydaggerjl-0.1.0.dist-info/METADATA
pydaggerjl-0.1.0.dist-info/WHEEL
pydaggerjl-0.1.0.dist-info/top_level.txt
pydaggerjl-0.1.0.dist-info/RECORD
