Metadata-Version: 2.1
Name: pydaggerjl
Version: 0.1.0
Summary: A Python interface to Dagger.jl
Home-page: https://github.com/jpsamaroo/pydaggerjl
Author: Julian P Samaroo
Author-email: jpsamaroo@gmail.com
Classifier: Programming Language :: Python :: 3
Classifier: License :: OSI Approved :: MIT License
Classifier: Operating System :: OS Independent
Requires-Python: >=3.6
License-File: LICENSE.md
Requires-Dist: numpy
Requires-Dist: juliacall
